[{"__type__":"cc.SpriteFrame","content":{"name":"bg_ts_e9c45877-7396-41ee-bd75-61bb7b39afca","texture":"e9xFh3c5ZB7r11Ybt7Oa/K","rect":[0,0,117,534],"offset":[0,0],"originalSize":[117,534],"capInsets":[49,154,44,153]}},[{"__type__":"cc.Prefab","_name":"UI_VideoTips","data":{"__id__":1}},{"__type__":"cc.Node","_name":"UI_VideoTips","_children":[{"__id__":2},{"__id__":3}],"_components":[{"__type__":"cc.Widget","node":{"__id__":1},"_alignFlags":45},{"__type__":"4ad20H2CK5G0qpr6qTYUVyJ","node":{"__id__":1},"bglight":{"__id__":7},"icon_zs":{"__id__":5},"icon_cl":{"__id__":6}}],"_prefab":{"__type__":"cc.PrefabInfo","root":{"__id__":1},"asset":{"__uuid__":"27NW+dEOxM85gqiabXINyZ"},"fileId":"3eFrrlJaJLK5+ZJDQRunJp"},"_contentSize":{"__type__":"cc.Size","width":1334,"height":750},"_trs":{"__type__":"TypedArray","ctor":"Float64Array","array":[667,375,0,0,0,0,1,1,1,1]}},{"__type__":"cc.Node","_name":"black","_parent":{"__id__":1},"_components":[{"__type__":"cc.Sprite","node":{"__id__":2},"_materials":[{"__uuid__":"ecpdLyjvZBwrvm+cedCcQy"}],"_spriteFrame":{"__uuid__":"7cn0zyKr9MFIkE8I3koKqT"},"_type":1,"_sizeMode":0},{"__type__":"cc.BlockInputEvents","node":{"__id__":2}},{"__type__":"cc.Widget","node":{"__id__":2},"_alignFlags":45,"_originalWidth":100,"_originalHeight":100}],"_prefab":{"__type__":"cc.PrefabInfo","root":{"__id__":1},"asset":{"__uuid__":"27NW+dEOxM85gqiabXINyZ"},"fileId":"dfbCPwMypJT7CO5p9/Acdn"},"_opacity":200,"_color":{"__type__":"cc.Color"},"_contentSize":{"__type__":"cc.Size","width":1334,"height":750},"_trs":{"__type__":"TypedArray","ctor":"Float64Array","array":[0,0,0,0,0,0,1,1,1,1]}},{"__type__":"cc.Node","_name":"panel","_parent":{"__id__":1},"_children":[{"__id__":4},{"__id__":5},{"__id__":6},{"__id__":7},{"__id__":8},{"__id__":9},{"__id__":10},{"__id__":11},{"__id__":14}],"_components":[{"__type__":"cc.Widget","node":{"__id__":3},"_alignFlags":45}],"_prefab":{"__type__":"cc.PrefabInfo","root":{"__id__":1},"asset":{"__uuid__":"27NW+dEOxM85gqiabXINyZ"},"fileId":"24xiXPpuhFFayHJq4vvcE8"},"_contentSize":{"__type__":"cc.Size","width":1334,"height":750},"_trs":{"__type__":"TypedArray","ctor":"Float64Array","array":[0,0,0,0,0,0,1,1,1,1]}},{"__type__":"cc.Node","_name":"bg_ts","_parent":{"__id__":3},"_components":[{"__type__":"cc.Sprite","node":{"__id__":4},"_materials":[{"__uuid__":"ecpdLyjvZBwrvm+cedCcQy"}],"_spriteFrame":{"__uuid__":"1fEG218MpMtqANzsiANVkl"},"_type":2,"_sizeMode":0},{"__type__":"cc.Widget","node":{"__id__":4},"_alignFlags":5,"_top":116.71299999999998,"_bottom":115.28699999999999,"_originalHeight":534}],"_prefab":{"__type__":"cc.PrefabInfo","root":{"__id__":1},"asset":{"__uuid__":"27NW+dEOxM85gqiabXINyZ"},"fileId":"51/LcZIPFO06UmP5TGtI4Y"},"_contentSize":{"__type__":"cc.Size","width":517,"height":518},"_trs":{"__type__":"TypedArray","ctor":"Float64Array","array":[0,-0.7130000000000223,0,0,0,0,1,1,1,1]}},{"__type__":"cc.Node","_name":"title_mfzs","_parent":{"__id__":3},"_components":[{"__type__":"cc.Label","node":{"__id__":5},"_materials":[{"__uuid__":"ecpdLyjvZBwrvm+cedCcQy"}],"_useOriginalSize":false,"_string":"Free Gems","_N$string":"Free Gems","_fontSize":80,"_lineHeight":80,"_N$file":{"__uuid__":"80dHGG+1BJRqwfawApdFdZ"},"_isSystemFontUsed":false,"_spacingX":-3,"_N$horizontalAlign":1,"_N$verticalAlign":1}],"_prefab":{"__type__":"cc.PrefabInfo","root":{"__id__":1},"asset":{"__uuid__":"27NW+dEOxM85gqiabXINyZ"},"fileId":"8ei/OB63VAFK2o33henoyp"},"_color":{"__type__":"cc.Color","r":221,"g":191,"b":251},"_contentSize":{"__type__":"cc.Size","width":370.86,"height":100.8},"_trs":{"__type__":"TypedArray","ctor":"Float64Array","array":[0,211.792,0,0,0,0,1,0.5,0.5,1]}},{"__type__":"cc.Node","_name":"title_mfcl","_parent":{"__id__":3},"_active":false,"_components":[{"__type__":"cc.Label","node":{"__id__":6},"_materials":[{"__uuid__":"ecpdLyjvZBwrvm+cedCcQy"}],"_useOriginalSize":false,"_string":"Free Gears","_N$string":"Free Gears","_fontSize":80,"_lineHeight":80,"_N$file":{"__uuid__":"80dHGG+1BJRqwfawApdFdZ"},"_isSystemFontUsed":false,"_spacingX":-3,"_N$horizontalAlign":1,"_N$verticalAlign":1}],"_prefab":{"__type__":"cc.PrefabInfo","root":{"__id__":1},"asset":{"__uuid__":"27NW+dEOxM85gqiabXINyZ"},"fileId":"c3uN9+EoJFR66lTmEnh7/g"},"_color":{"__type__":"cc.Color","r":221,"g":191,"b":251},"_contentSize":{"__type__":"cc.Size","width":370.86,"height":100.8},"_trs":{"__type__":"TypedArray","ctor":"Float64Array","array":[0,211.792,0,0,0,0,1,0.5,0.5,1]}},{"__type__":"cc.Node","_name":"bg_light","_parent":{"__id__":3},"_components":[{"__type__":"cc.Sprite","node":{"__id__":7},"_materials":[{"__uuid__":"ecpdLyjvZBwrvm+cedCcQy"}],"_spriteFrame":{"__uuid__":"77qIxxHwhEDZIXe62IgV0L"}}],"_prefab":{"__type__":"cc.PrefabInfo","root":{"__id__":1},"asset":{"__uuid__":"27NW+dEOxM85gqiabXINyZ"},"fileId":"abc3+TfclJVZXwpO+6iVlk"},"_contentSize":{"__type__":"cc.Size","width":436,"height":435},"_trs":{"__type__":"TypedArray","ctor":"Float64Array","array":[0,-46.713,0,0,0,0,1,1,1,1]}},{"__type__":"cc.Node","_name":"icon_diamond","_parent":{"__id__":3},"_components":[{"__type__":"cc.Sprite","node":{"__id__":8},"_materials":[{"__uuid__":"ecpdLyjvZBwrvm+cedCcQy"}],"_spriteFrame":{"__uuid__":"bdOW414PFATpJIyaoBrSG6"}}],"_prefab":{"__type__":"cc.PrefabInfo","root":{"__id__":1},"asset":{"__uuid__":"27NW+dEOxM85gqiabXINyZ"},"fileId":"c5GMBbvx9B9YriU5RvwlDX"},"_contentSize":{"__type__":"cc.Size","width":285,"height":202},"_trs":{"__type__":"TypedArray","ctor":"Float64Array","array":[0,34.092,0,0,0,0,1,1,1,1]}},{"__type__":"cc.Node","_name":"icon_gear","_parent":{"__id__":3},"_active":false,"_components":[{"__type__":"cc.Sprite","node":{"__id__":9},"_materials":[{"__uuid__":"ecpdLyjvZBwrvm+cedCcQy"}],"_spriteFrame":{"__uuid__":"cavt+QzvZMDJ54YAHcjSbx"},"_sizeMode":0}],"_prefab":{"__type__":"cc.PrefabInfo","root":{"__id__":1},"asset":{"__uuid__":"27NW+dEOxM85gqiabXINyZ"},"fileId":"0a8l9ykNhGdKCZlUeNK7ta"},"_contentSize":{"__type__":"cc.Size","width":177,"height":158},"_trs":{"__type__":"TypedArray","ctor":"Float64Array","array":[-7.046,22.029,0,0,0,0,1,1,1,1]}},{"__type__":"cc.Node","_name":"btn_x","_parent":{"__id__":3},"_components":[{"__type__":"cc.Sprite","node":{"__id__":10},"_materials":[{"__uuid__":"ecpdLyjvZBwrvm+cedCcQy"}],"_spriteFrame":{"__uuid__":"95ZTS8CtJKvKgaTEdstrLP"}},{"__type__":"cc.Button","node":{"__id__":10},"_normalMaterial":{"__uuid__":"ecpdLyjvZBwrvm+cedCcQy"},"zoomScale":0.95,"clickEvents":[{"__type__":"cc.ClickEvent","target":{"__id__":1},"_componentId":"4ad20H2CK5G0qpr6qTYUVyJ","handler":"onEvent_btn_close"}],"_N$transition":3,"transition":3}],"_prefab":{"__type__":"cc.PrefabInfo","root":{"__id__":1},"asset":{"__uuid__":"27NW+dEOxM85gqiabXINyZ"},"fileId":"0cqOFGUOlNlZil0nZ3jCu1"},"_contentSize":{"__type__":"cc.Size","width":35,"height":36},"_trs":{"__type__":"TypedArray","ctor":"Float64Array","array":[220,223.287,0,0,0,0,1,1,1,1]}},{"__type__":"cc.Node","_name":"btn_greem","_parent":{"__id__":3},"_children":[{"__id__":12},{"__id__":13}],"_components":[{"__type__":"cc.Sprite","node":{"__id__":11},"_materials":[{"__uuid__":"ecpdLyjvZBwrvm+cedCcQy"}],"_spriteFrame":{"__uuid__":"6csvhWIOpK+6VmFnuwQwlu"},"_type":1,"_sizeMode":0,"_isTrimmedMode":false},{"__type__":"cc.Button","node":{"__id__":11},"_normalMaterial":{"__uuid__":"ecpdLyjvZBwrvm+cedCcQy"},"zoomScale":0.95,"clickEvents":[{"__type__":"cc.ClickEvent","target":{"__id__":1},"_componentId":"4ad20H2CK5G0qpr6qTYUVyJ","handler":"onEvent_btn_getReward_doubleCoin"}],"_N$transition":3,"transition":3}],"_prefab":{"__type__":"cc.PrefabInfo","root":{"__id__":1},"asset":{"__uuid__":"27NW+dEOxM85gqiabXINyZ"},"fileId":"2bmQsoYVBBpZZkkTtPvVcW"},"_contentSize":{"__type__":"cc.Size","width":255,"height":92},"_trs":{"__type__":"TypedArray","ctor":"Float64Array","array":[0,-192.991,0,0,0,0,1,1,1,1]}},{"__type__":"cc.Node","_name":"icon_sp","_parent":{"__id__":11},"_components":[{"__type__":"cc.Sprite","node":{"__id__":12},"_materials":[{"__uuid__":"ecpdLyjvZBwrvm+cedCcQy"}],"_spriteFrame":{"__uuid__":"55EVKhWk1LoqiFGW3Kbn+7"}}],"_prefab":{"__type__":"cc.PrefabInfo","root":{"__id__":1},"asset":{"__uuid__":"27NW+dEOxM85gqiabXINyZ"},"fileId":"21RLkeWGlDTIaalmbQgDhN"},"_color":{"__type__":"cc.Color","r":35,"g":112,"b":45},"_contentSize":{"__type__":"cc.Size","width":44,"height":42},"_trs":{"__type__":"TypedArray","ctor":"Float64Array","array":[-71.253,4.167,0,0,0,0,1,1,1,1]}},{"__type__":"cc.Node","_name":"font_sblq","_parent":{"__id__":11},"_components":[{"__type__":"cc.Label","node":{"__id__":13},"_materials":[{"__uuid__":"ecpdLyjvZBwrvm+cedCcQy"}],"_useOriginalSize":false,"_string":"Claim","_N$string":"Claim","_fontSize":80,"_lineHeight":80,"_N$file":{"__uuid__":"80dHGG+1BJRqwfawApdFdZ"},"_isSystemFontUsed":false,"_spacingX":-3,"_N$horizontalAlign":1,"_N$verticalAlign":1},{"__type__":"cc.LabelOutline","node":{"__id__":13},"_color":{"__type__":"cc.Color","r":35,"g":112,"b":45},"_width":8}],"_prefab":{"__type__":"cc.PrefabInfo","root":{"__id__":1},"asset":{"__uuid__":"27NW+dEOxM85gqiabXINyZ"},"fileId":"2efp1OuFxN+7nBeH3BMeVg"},"_contentSize":{"__type__":"cc.Size","width":226.08,"height":116.8},"_trs":{"__type__":"TypedArray","ctor":"Float64Array","array":[30,5.052,0,0,0,0,1,0.5,0.5,0.5]}},{"__type__":"cc.Node","_name":"numLabel","_parent":{"__id__":3},"_components":[{"__type__":"cc.Label","node":{"__id__":14},"_materials":[{"__uuid__":"ecpdLyjvZBwrvm+cedCcQy"}],"_useOriginalSize":false,"_string":"+50","_N$string":"+50","_fontSize":80,"_lineHeight":80,"_N$file":{"__uuid__":"80dHGG+1BJRqwfawApdFdZ"},"_isSystemFontUsed":false,"_spacingX":-3,"_N$horizontalAlign":1,"_N$verticalAlign":1},{"__type__":"cc.LabelOutline","node":{"__id__":14},"_color":{"__type__":"cc.Color","r":74,"g":37,"b":150},"_width":6}],"_prefab":{"__type__":"cc.PrefabInfo","root":{"__id__":1},"asset":{"__uuid__":"27NW+dEOxM85gqiabXINyZ"},"fileId":"48CITrsk5NT6MmFqt90hfS"},"_contentSize":{"__type__":"cc.Size","width":140.63,"height":112.8},"_trs":{"__type__":"TypedArray","ctor":"Float64Array","array":[0,-103.354,0,0,0,0,1,0.5,0.5,1]}}],{"__type__":"cc.SpriteFrame","content":{"name":"icon_sp_ad2","texture":"bdN2OKwS9De6E9MAqePLnw","rect":[0,0,44,42],"offset":[0,0],"originalSize":[44,42],"capInsets":[0,0,0,0]}},{"__type__":"cc.SpriteFrame","content":{"name":"btn_greem","texture":"14K/81+HRNzL6Sp3NgpAUM","rect":[0,0,64,92],"offset":[0,0],"originalSize":[64,92],"capInsets":[26,0,26,0]}},{"__type__":"cc.SpriteFrame","content":{"name":"bg_light","texture":"78dIK2OT1OxIng6Y8SQRI2","rect":[0,0,436,435],"offset":[0,0],"originalSize":[436,435],"capInsets":[0,0,0,0]}},{"__type__":"cc.SpriteFrame","content":{"name":"rect_2","texture":"0buWSLwEJMgYXYPTz1L1bQ","rect":[0,0,2,2],"offset":[0,0],"originalSize":[2,2],"capInsets":[1,1,1,1]}},{"__type__":"cc.SpriteFrame","content":{"name":"btn_x","texture":"382Vjcb65DYpIqSbdIE33l","rect":[0,0,35,36],"offset":[0,0],"originalSize":[35,36],"capInsets":[0,0,0,0]}},{"__type__":"cc.SpriteFrame","content":{"name":"gui_many_gem","texture":"c8G3WEzGhH+r+k+6YJBUzN","rect":[0,0,285,202],"offset":[0,0],"originalSize":[285,202],"capInsets":[0,0,0,0]}},{"__type__":"cc.SpriteFrame","content":{"name":"gui_cl_box2","texture":"3cmLjmAGJP4ZkcXHzY7SMG","rect":[0,0,157,138],"offset":[0,0],"originalSize":[157,138],"capInsets":[0,0,0,0]}}]